setup.cfg
setup.py
FOFA.egg-info/PKG-INFO
FOFA.egg-info/SOURCES.txt
FOFA.egg-info/dependency_links.txt
FOFA.egg-info/top_level.txt
fofa/__init__.py
fofa/client.py
fofa/poc/__init__.py
fofa/src/__init__.py