Metadata-Version: 1.1
Name: FOFA
Version: 1.0.2
Summary: Python library for FOFA (https://fofa.info)
Home-page: https://github.com/fofa-dev/FofaSDK-python
Author: gcr
Author-email: yzjjaheim@163.com
License: UNKNOWN
Platform: UNKNOWN
Classifier: Intended Audience :: Developers
Classifier: License :: OSI Approved :: MIT License
Classifier: Operating System :: OS Independent
Classifier: Programming Language :: Python
Classifier: Topic :: Software Development :: Libraries :: Python Modules
